rtm_fast_unification/__init__.py
rtm_fast_unification/DSCode/__init__.py
rtm_fast_unification/DSCode/common_function.py
rtm_fast_unification/DSCode/common_utilities_registry.py
rtm_fast_unification/DSCode/config_data_registry.py
rtm_fast_unification/DSCode/ds_code_registry.py
rtm_fast_unification/DSCode/requirements.txt
rtm_fast_unification/DSCode/library/__init__.py
rtm_fast_unification/DSCode/library/ds_code_test_measurement.py
rtm_fast_unification/DSCode/library/ds_code_test_plan.py
rtm_fast_unification/DSCode/library/ds_common_functions.py
rtm_fast_unification/DSCode/library/ds/__init__.py
rtm_fast_unification/DSCode/library/ds/feature/cntrl_store_gen/cntrl_stores_master.py
rtm_fast_unification/DSCode/library/ds/feature/rsv_estimation/rsv_estimate_master.py
rtm_fast_unification/DSCode/library/ds/feature/target_estimation/target_estimate_master.py
rtm_fast_unification/DSCode/library/ds/feature/test_measurement_cal/test_measurement_master.py
rtm_fast_unification/DSCode/library/ds/feature/test_store_gen/test_stores_master.py
rtm_fast_unification/DSCode/library/object_creation/__init__.py
rtm_fast_unification/DSCode/library/object_creation/create_object.py
rtm_fast_unification/DSCode/library/sql/__init__.py
rtm_fast_unification/DSCode/library/sql/sales_master.py
rtm_fast_unification/DSCode/library/sql/stores_master.py
rtm_fast_unification/DSCode/library/sql/utility/__init__.py
rtm_fast_unification/DSCode/library/sql/utility/sql_utility.py
rtm_fast_unification/DSCode/regions/__init__.py
rtm_fast_unification/DSCode/regions/UK/__init__.py
rtm_fast_unification/DSCode/regions/UK/common_utility.py
rtm_fast_unification/DSCode/regions/UK/config_data.py
rtm_fast_unification/DSCode/regions/UK/ds_code.py
rtm_fast_unification/DSCode/regions/UK/upload_templates/Control_Pairs_Pool_Upload_Template_UK.xlsx
rtm_fast_unification/DSCode/regions/UK/upload_templates/Test_Control_Pairs_Upload_Template_UK.xlsx
rtm_fast_unification-0.0.1.dist-info/METADATA
rtm_fast_unification-0.0.1.dist-info/WHEEL
rtm_fast_unification-0.0.1.dist-info/licenses/LICENSE
rtm_fast_unification-0.0.1.dist-info/RECORD
